shocurasy/__init__.py
shocurasy/shortcut.py
testpongpong-0.0.1.dist-info/LICENSE
testpongpong-0.0.1.dist-info/METADATA
testpongpong-0.0.1.dist-info/WHEEL
testpongpong-0.0.1.dist-info/top_level.txt
testpongpong-0.0.1.dist-info/RECORD
