Metadata-Version: 2.1
Name: testpongpong
Version: 0.0.1
Summary: Shortcuts funcitions.
Home-page: https://github.com/lotexiu/shocurasy
Author: Aleph (Lotexiu)
Author-email: <alephcostamelo@gmail.com>
License: UNKNOWN
Keywords: python,sqlite,keyboard,pixel capture,Pillow,teminal
Platform: UNKNOWN
Classifier: Development Status :: 1 - Planning
Classifier: Intended Audience :: Developers
Classifier: Programming Language :: Python :: 3
Classifier: License :: OSI Approved :: MIT License
Classifier: Operating System :: MacOS :: MacOS X
Classifier: Operating System :: Microsoft :: Windows
License-File: LICENSE
Requires-Dist: keyboard
Requires-Dist: pyautogui
Requires-Dist: pydirectinput
Requires-Dist: Pillow
Requires-Dist: mido
